{"all_car_data": [{"calculation": {"type": "zurich_vehicle_type-calculation-9", "vehicle_type": "medium_car", "kilometers": 4.472135954989157e-05}}], "all_flight_data": [{"calculation": {"type": "zurich_vehicle_type-calculation-9", "from_airport": "LAX", "to_airport": "LHR", "travel_class": "economy", "travel_route": "oneway", "passengers": 300}}, {"calculation": {"type": "zurich_vehicle_type-calculation-9", "from_airport": "LAX", "to_airport": "LHR", "travel_class": "economy", "travel_route": "oneway", "passengers": 300}}, {"calculation": {"type": "zurich_vehicle_type-calculation-9", "from_airport": "LAX", "to_airport": "LHR", "travel_class": "economy", "travel_route": "oneway", "passengers": 300}}]}